[
  {
    "id": "bluey_jututs_1",
    "title": "布鲁伊 第一季 第1集",
    "category": "bluey",
    "cover": "/videos/thumbs/bluey_cover_common.jpg",
    "video": "https://hn.bfvvs.com/play/0dNQ19Nb/index.m3u8",
    "isHls": true,
    "duration": "07:00",
    "author": "Bluey"
  },
  {
    "id": "bluey_jututs_2",
    "title": "布鲁伊 第一季 第2集",
    "category": "bluey",
    "cover": "/videos/thumbs/bluey_cover_common.jpg",
    "video": "https://hn.bfvvs.com/play/ZdPXJz6d/index.m3u8",
    "isHls": true,
    "duration": "07:00",
    "author": "Bluey"
  },
  {
    "id": "bluey_jututs_3",
    "title": "布鲁伊 第一季 第3集",
    "category": "bluey",
    "cover": "/videos/thumbs/bluey_cover_common.jpg",
    "video": "https://hn.bfvvs.com/play/xbopJAYd/index.m3u8",
    "isHls": true,
    "duration": "07:00",
    "author": "Bluey"
  },
  {
    "id": "bluey_jututs_4",
    "title": "布鲁伊 第一季 第4集",
    "category": "bluey",
    "cover": "/videos/thumbs/bluey_cover_common.jpg",
    "video": "https://hn.bfvvs.com/play/9avKJZnb/index.m3u8",
    "isHls": true,
    "duration": "07:00",
    "author": "Bluey"
  },
  {
    "id": "bluey_jututs_5",
    "title": "布鲁伊 第一季 第5集",
    "category": "bluey",
    "cover": "/videos/thumbs/bluey_cover_common.jpg",
    "video": "https://hn.bfvvs.com/play/wdLMB7je/index.m3u8",
    "isHls": true,
    "duration": "07:00",
    "author": "Bluey"
  },
  {
    "id": "bluey_jututs_6",
    "title": "布鲁伊 第一季 第6集",
    "category": "bluey",
    "cover": "/videos/thumbs/bluey_cover_common.jpg",
    "video": "https://hn.bfvvs.com/play/mbk9M2Ke/index.m3u8",
    "isHls": true,
    "duration": "07:00",
    "author": "Bluey"
  },
  {
    "id": "bluey_jututs_7",
    "title": "布鲁伊 第一季 第7集",
    "category": "bluey",
    "cover": "/videos/thumbs/bluey_cover_common.jpg",
    "video": "https://hn.bfvvs.com/play/xe7NJAQd/index.m3u8",
    "isHls": true,
    "duration": "07:00",
    "author": "Bluey"
  },
  {
    "id": "bluey_jututs_8",
    "title": "布鲁伊 第一季 第8集",
    "category": "bluey",
    "cover": "/videos/thumbs/bluey_cover_common.jpg",
    "video": "https://hn.bfvvs.com/play/Qe1x76Gd/index.m3u8",
    "isHls": true,
    "duration": "07:00",
    "author": "Bluey"
  },
  {
    "id": "bluey_jututs_9",
    "title": "布鲁伊 第一季 第9集",
    "category": "bluey",
    "cover": "/videos/thumbs/bluey_cover_common.jpg",
    "video": "https://hn.bfvvs.com/play/xbopJAXd/index.m3u8",
    "isHls": true,
    "duration": "07:00",
    "author": "Bluey"
  },
  {
    "id": "bluey_jututs_10",
    "title": "布鲁伊 第一季 第10集",
    "category": "bluey",
    "cover": "/videos/thumbs/bluey_cover_common.jpg",
    "video": "https://hn.bfvvs.com/play/NbWkBLnb/index.m3u8",
    "isHls": true,
    "duration": "07:00",
    "author": "Bluey"
  },
  {
    "id": "bluey_jututs_11",
    "title": "布鲁伊 第一季 第11集",
    "category": "bluey",
    "cover": "/videos/thumbs/bluey_cover_common.jpg",
    "video": "https://hn.bfvvs.com/play/PdR2BlYd/index.m3u8",
    "isHls": true,
    "duration": "07:00",
    "author": "Bluey"
  },
  {
    "id": "bluey_jututs_12",
    "title": "布鲁伊 第一季 第12集",
    "category": "bluey",
    "cover": "/videos/thumbs/bluey_cover_common.jpg",
    "video": "https://hn.bfvvs.com/play/7e5J0RXa/index.m3u8",
    "isHls": true,
    "duration": "07:00",
    "author": "Bluey"
  },
  {
    "id": "bluey_jututs_13",
    "title": "布鲁伊 第一季 第13集",
    "category": "bluey",
    "cover": "/videos/thumbs/bluey_cover_common.jpg",
    "video": "https://hn.bfvvs.com/play/zbqw8Qke/index.m3u8",
    "isHls": true,
    "duration": "07:00",
    "author": "Bluey"
  },
  {
    "id": "bluey_jututs_14",
    "title": "布鲁伊 第一季 第14集",
    "category": "bluey",
    "cover": "/videos/thumbs/bluey_cover_common.jpg",
    "video": "https://hn.bfvvs.com/play/xbopJjLd/index.m3u8",
    "isHls": true,
    "duration": "07:00",
    "author": "Bluey"
  },
  {
    "id": "bluey_jututs_15",
    "title": "布鲁伊 第一季 第15集",
    "category": "bluey",
    "cover": "/videos/thumbs/bluey_cover_common.jpg",
    "video": "https://hn.bfvvs.com/play/Le3BJQ9d/index.m3u8",
    "isHls": true,
    "duration": "07:00",
    "author": "Bluey"
  },
  {
    "id": "bluey_jututs_16",
    "title": "布鲁伊 第一季 第16集",
    "category": "bluey",
    "cover": "/videos/thumbs/bluey_cover_common.jpg",
    "video": "https://hn.bfvvs.com/play/kazVl62a/index.m3u8",
    "isHls": true,
    "duration": "07:00",
    "author": "Bluey"
  },
  {
    "id": "bluey_jututs_17",
    "title": "布鲁伊 第一季 第17集",
    "category": "bluey",
    "cover": "/videos/thumbs/bluey_cover_common.jpg",
    "video": "https://hn.bfvvs.com/play/oeErQxla/index.m3u8",
    "isHls": true,
    "duration": "07:00",
    "author": "Bluey"
  },
  {
    "id": "bluey_jututs_18",
    "title": "布鲁伊 第一季 第18集",
    "category": "bluey",
    "cover": "/videos/thumbs/bluey_cover_common.jpg",
    "video": "https://hn.bfvvs.com/play/mbk9M2ve/index.m3u8",
    "isHls": true,
    "duration": "07:00",
    "author": "Bluey"
  },
  {
    "id": "bluey_jututs_19",
    "title": "布鲁伊 第一季 第19集",
    "category": "bluey",
    "cover": "/videos/thumbs/bluey_cover_common.jpg",
    "video": "https://hn.bfvvs.com/play/QbYoXyYe/index.m3u8",
    "isHls": true,
    "duration": "07:00",
    "author": "Bluey"
  },
  {
    "id": "bluey_jututs_20",
    "title": "布鲁伊 第一季 第20集",
    "category": "bluey",
    "cover": "/videos/thumbs/bluey_cover_common.jpg",
    "video": "https://hn.bfvvs.com/play/7axOjoBe/index.m3u8",
    "isHls": true,
    "duration": "07:00",
    "author": "Bluey"
  },
  {
    "id": "bluey_jututs_21",
    "title": "布鲁伊 第一季 第21集",
    "category": "bluey",
    "cover": "/videos/thumbs/bluey_cover_common.jpg",
    "video": "https://hn.bfvvs.com/play/Pe9RX1Ya/index.m3u8",
    "isHls": true,
    "duration": "07:00",
    "author": "Bluey"
  },
  {
    "id": "bluey_jututs_22",
    "title": "布鲁伊 第一季 第22集",
    "category": "bluey",
    "cover": "/videos/thumbs/bluey_cover_common.jpg",
    "video": "https://hn.bfvvs.com/play/neg1X7kb/index.m3u8",
    "isHls": true,
    "duration": "07:00",
    "author": "Bluey"
  },
  {
    "id": "bluey_jututs_23",
    "title": "布鲁伊 第一季 第23集",
    "category": "bluey",
    "cover": "/videos/thumbs/bluey_cover_common.jpg",
    "video": "https://hn.bfvvs.com/play/wdLMBPDe/index.m3u8",
    "isHls": true,
    "duration": "07:00",
    "author": "Bluey"
  },
  {
    "id": "bluey_jututs_24",
    "title": "布鲁伊 第一季 第24集",
    "category": "bluey",
    "cover": "/videos/thumbs/bluey_cover_common.jpg",
    "video": "https://hn.bfvvs.com/play/0dNQ108b/index.m3u8",
    "isHls": true,
    "duration": "07:00",
    "author": "Bluey"
  },
  {
    "id": "bluey_jututs_25",
    "title": "布鲁伊 第一季 第25集",
    "category": "bluey",
    "cover": "/videos/thumbs/bluey_cover_common.jpg",
    "video": "https://hn.bfvvs.com/play/vbmlXERa/index.m3u8",
    "isHls": true,
    "duration": "07:00",
    "author": "Bluey"
  },
  {
    "id": "bluey_jututs_26",
    "title": "布鲁伊 第一季 第26集",
    "category": "bluey",
    "cover": "/videos/thumbs/bluey_cover_common.jpg",
    "video": "https://hn.bfvvs.com/play/zbqw8Qye/index.m3u8",
    "isHls": true,
    "duration": "07:00",
    "author": "Bluey"
  },
  {
    "id": "bluey_jututs_27",
    "title": "布鲁伊 第一季 第27集",
    "category": "bluey",
    "cover": "/videos/thumbs/bluey_cover_common.jpg",
    "video": "https://hn.bfvvs.com/play/0dNQ17vb/index.m3u8",
    "isHls": true,
    "duration": "07:00",
    "author": "Bluey"
  },
  {
    "id": "bluey_jututs_28",
    "title": "布鲁伊 第一季 第28集",
    "category": "bluey",
    "cover": "/videos/thumbs/bluey_cover_common.jpg",
    "video": "https://hn.bfvvs.com/play/NbWkBqob/index.m3u8",
    "isHls": true,
    "duration": "07:00",
    "author": "Bluey"
  },
  {
    "id": "bluey_jututs_29",
    "title": "布鲁伊 第一季 第29集",
    "category": "bluey",
    "cover": "/videos/thumbs/bluey_cover_common.jpg",
    "video": "https://hn.bfvvs.com/play/oeErQKga/index.m3u8",
    "isHls": true,
    "duration": "07:00",
    "author": "Bluey"
  },
  {
    "id": "bluey_jututs_30",
    "title": "布鲁伊 第一季 第30集",
    "category": "bluey",
    "cover": "/videos/thumbs/bluey_cover_common.jpg",
    "video": "https://hn.bfvvs.com/play/neg1Xxrb/index.m3u8",
    "isHls": true,
    "duration": "07:00",
    "author": "Bluey"
  },
  {
    "id": "bluey_jututs_31",
    "title": "布鲁伊 第一季 第31集",
    "category": "bluey",
    "cover": "/videos/thumbs/bluey_cover_common.jpg",
    "video": "https://hn.bfvvs.com/play/QdJGXYKe/index.m3u8",
    "isHls": true,
    "duration": "07:00",
    "author": "Bluey"
  },
  {
    "id": "bluey_jututs_32",
    "title": "布鲁伊 第一季 第32集",
    "category": "bluey",
    "cover": "/videos/thumbs/bluey_cover_common.jpg",
    "video": "https://hn.bfvvs.com/play/Le3BJwpd/index.m3u8",
    "isHls": true,
    "duration": "07:00",
    "author": "Bluey"
  },
  {
    "id": "bluey_jututs_33",
    "title": "布鲁伊 第一季 第33集",
    "category": "bluey",
    "cover": "/videos/thumbs/bluey_cover_common.jpg",
    "video": "https://hn.bfvvs.com/play/7e5J0lYa/index.m3u8",
    "isHls": true,
    "duration": "07:00",
    "author": "Bluey"
  },
  {
    "id": "bluey_jututs_34",
    "title": "布鲁伊 第一季 第34集",
    "category": "bluey",
    "cover": "/videos/thumbs/bluey_cover_common.jpg",
    "video": "https://hn.bfvvs.com/play/9avKJj8b/index.m3u8",
    "isHls": true,
    "duration": "07:00",
    "author": "Bluey"
  },
  {
    "id": "bluey_jututs_35",
    "title": "布鲁伊 第一季 第35集",
    "category": "bluey",
    "cover": "/videos/thumbs/bluey_cover_common.jpg",
    "video": "https://hn.bfvvs.com/play/mbk9MoJe/index.m3u8",
    "isHls": true,
    "duration": "07:00",
    "author": "Bluey"
  },
  {
    "id": "bluey_jututs_36",
    "title": "布鲁伊 第一季 第36集",
    "category": "bluey",
    "cover": "/videos/thumbs/bluey_cover_common.jpg",
    "video": "https://hn.bfvvs.com/play/QbYoXQAe/index.m3u8",
    "isHls": true,
    "duration": "07:00",
    "author": "Bluey"
  },
  {
    "id": "bluey_jututs_37",
    "title": "布鲁伊 第一季 第37集",
    "category": "bluey",
    "cover": "/videos/thumbs/bluey_cover_common.jpg",
    "video": "https://hn.bfvvs.com/play/6dBlEnQa/index.m3u8",
    "isHls": true,
    "duration": "07:00",
    "author": "Bluey"
  },
  {
    "id": "bluey_jututs_38",
    "title": "布鲁伊 第一季 第38集",
    "category": "bluey",
    "cover": "/videos/thumbs/bluey_cover_common.jpg",
    "video": "https://hn.bfvvs.com/play/QdJGXNye/index.m3u8",
    "isHls": true,
    "duration": "07:00",
    "author": "Bluey"
  },
  {
    "id": "bluey_jututs_39",
    "title": "布鲁伊 第一季 第39集",
    "category": "bluey",
    "cover": "/videos/thumbs/bluey_cover_common.jpg",
    "video": "https://hn.bfvvs.com/play/kazVlBqa/index.m3u8",
    "isHls": true,
    "duration": "07:00",
    "author": "Bluey"
  },
  {
    "id": "bluey_jututs_40",
    "title": "布鲁伊 第一季 第40集",
    "category": "bluey",
    "cover": "/videos/thumbs/bluey_cover_common.jpg",
    "video": "https://hn.bfvvs.com/play/zbqw8V7e/index.m3u8",
    "isHls": true,
    "duration": "07:00",
    "author": "Bluey"
  },
  {
    "id": "bluey_jututs_41",
    "title": "布鲁伊 第一季 第41集",
    "category": "bluey",
    "cover": "/videos/thumbs/bluey_cover_common.jpg",
    "video": "https://hn.bfvvs.com/play/neg1Xnjb/index.m3u8",
    "isHls": true,
    "duration": "07:00",
    "author": "Bluey"
  },
  {
    "id": "bluey_jututs_42",
    "title": "布鲁伊 第一季 第42集",
    "category": "bluey",
    "cover": "/videos/thumbs/bluey_cover_common.jpg",
    "video": "https://hn.bfvvs.com/play/Pe9RXgza/index.m3u8",
    "isHls": true,
    "duration": "07:00",
    "author": "Bluey"
  },
  {
    "id": "bluey_jututs_43",
    "title": "布鲁伊 第一季 第43集",
    "category": "bluey",
    "cover": "/videos/thumbs/bluey_cover_common.jpg",
    "video": "https://hn.bfvvs.com/play/xe7NJ9Od/index.m3u8",
    "isHls": true,
    "duration": "07:00",
    "author": "Bluey"
  },
  {
    "id": "bluey_jututs_44",
    "title": "布鲁伊 第一季 第44集",
    "category": "bluey",
    "cover": "/videos/thumbs/bluey_cover_common.jpg",
    "video": "https://hn.bfvvs.com/play/7axOj2Pe/index.m3u8",
    "isHls": true,
    "duration": "07:00",
    "author": "Bluey"
  },
  {
    "id": "bluey_jututs_45",
    "title": "布鲁伊 第一季 第45集",
    "category": "bluey",
    "cover": "/videos/thumbs/bluey_cover_common.jpg",
    "video": "https://hn.bfvvs.com/play/NbWkBWxb/index.m3u8",
    "isHls": true,
    "duration": "07:00",
    "author": "Bluey"
  },
  {
    "id": "bluey_jututs_46",
    "title": "布鲁伊 第一季 第46集",
    "category": "bluey",
    "cover": "/videos/thumbs/bluey_cover_common.jpg",
    "video": "https://hn.bfvvs.com/play/vbmlXOna/index.m3u8",
    "isHls": true,
    "duration": "07:00",
    "author": "Bluey"
  },
  {
    "id": "bluey_jututs_47",
    "title": "布鲁伊 第一季 第47集",
    "category": "bluey",
    "cover": "/videos/thumbs/bluey_cover_common.jpg",
    "video": "https://hn.bfvvs.com/play/6dBlENWa/index.m3u8",
    "isHls": true,
    "duration": "07:00",
    "author": "Bluey"
  },
  {
    "id": "bluey_jututs_48",
    "title": "布鲁伊 第一季 第48集",
    "category": "bluey",
    "cover": "/videos/thumbs/bluey_cover_common.jpg",
    "video": "https://hn.bfvvs.com/play/9avKJlMb/index.m3u8",
    "isHls": true,
    "duration": "07:00",
    "author": "Bluey"
  },
  {
    "id": "bluey_jututs_49",
    "title": "布鲁伊 第一季 第49集",
    "category": "bluey",
    "cover": "/videos/thumbs/bluey_cover_common.jpg",
    "video": "https://hn.bfvvs.com/play/PdR2BLVd/index.m3u8",
    "isHls": true,
    "duration": "07:00",
    "author": "Bluey"
  },
  {
    "id": "bluey_jututs_50",
    "title": "布鲁伊 第一季 第50集",
    "category": "bluey",
    "cover": "/videos/thumbs/bluey_cover_common.jpg",
    "video": "https://hn.bfvvs.com/play/ZdPXJMAd/index.m3u8",
    "isHls": true,
    "duration": "07:00",
    "author": "Bluey"
  },
  {
    "id": "bluey_jututs_51",
    "title": "布鲁伊 第一季 第51集",
    "category": "bluey",
    "cover": "/videos/thumbs/bluey_cover_common.jpg",
    "video": "https://hn.bfvvs.com/play/Qe1x79Zd/index.m3u8",
    "isHls": true,
    "duration": "07:00",
    "author": "Bluey"
  },
  {
    "id": "bluey_jututs_52",
    "title": "布鲁伊 第一季 第52集",
    "category": "bluey",
    "cover": "/videos/thumbs/bluey_cover_common.jpg",
    "video": "https://hn.bfvvs.com/play/vbmlXy3a/index.m3u8",
    "isHls": true,
    "duration": "07:00",
    "author": "Bluey"
  }
]